[{"name":"entity.Sao-Paulo-SP.SP.Cidadeape-Associacao-pela-Mobilidade-a-Pe-em-Sao-Paulo","imports":["abordagem.comunicacao","abordagem.educacao","abordagem.legislacao","abordagem.mobilizacao","abordagem.pesquisa","financiamento.nenhuma","objeto-de-atuacao.infraestrutura","objeto-de-atuacao.microacessibilidade","objeto-de-atuacao.planejamento-urbano","dificuldades.escassez-de-voluntarios","dificuldades.apoio-politico"],"estado":"SP","cidade":"São Paulo (SP)"},{"name":"entity.Porto-Alegre-RS.RS.WRI-Brasil-Cidades-Sustentaveis","imports":["abordagem.comunicacao","abordagem.educacao","abordagem.legislacao","abordagem.pesquisa","financiamento.doacao-direta-filantropia","financiamento.edital","objeto-de-atuacao.bicicleta","objeto-de-atuacao.infraestrutura","objeto-de-atuacao.meio-ambiente","objeto-de-atuacao.microacessibilidade","objeto-de-atuacao.planejamento-urbano","objeto-de-atuacao.saude-e-qualidade-de-vida","dificuldades.acesso-a-info","dificuldades.apoio-politico","dificuldades.falta-de-conhecimento","dificuldades.apoio-politico"],"estado":"RS","cidade":"Porto Alegre (RS)"},{"name":"entity.Sao-Paulo-SP.SP.Mobilize","imports":["abordagem.educacao","abordagem.mobilizacao","abordagem.pesquisa","financiamento.patrocinio","objeto-de-atuacao.bicicleta","objeto-de-atuacao.infraestrutura","objeto-de-atuacao.microacessibilidade","objeto-de-atuacao.planejamento-urbano","objeto-de-atuacao.tecnologia-e-inovacao","dificuldades.financiamento"],"estado":"SP","cidade":"São Paulo (SP)"},{"name":"entity...Escola-de-Ativismo","imports":["financiamento.doacao-direta-filantropia"],"estado":"","cidade":""},{"name":"entity.Sao-Paulo-SP.SP.Cidade-Ativa","imports":["abordagem.comunicacao","abordagem.educacao","abordagem.intervencao","abordagem.mobilizacao","abordagem.pesquisa","abordagem.projetos","financiamento.doacao-direta-filantropia","financiamento.prestacao-de-servico","financiamento.voluntario","objeto-de-atuacao.infraestrutura","objeto-de-atuacao.planejamento-urbano","objeto-de-atuacao.saude-e-qualidade-de-vida","dificuldades.financiamento"],"estado":"SP","cidade":"São Paulo (SP)"},{"name":"entity.Sao-Paulo-SP.SP.Corrida-Amiga","imports":["abordagem.intervencao","abordagem.legislacao","abordagem.mobilizacao","financiamento.doacao-direta-filantropia","financiamento.prestacao-de-servico","financiamento.voluntario","financiamento.venda-de-produtos","objeto-de-atuacao.infraestrutura","objeto-de-atuacao.saude-e-qualidade-de-vida","objeto-de-atuacao.tecnologia-e-inovacao","dificuldades.financiamento","dificuldades.escassez-de-voluntarios"],"estado":"SP","cidade":"São Paulo (SP)"},{"name":"entity.Sao-Paulo-SP.SP.JBMC-Arquitetura-and-Urbanismo","imports":["abordagem.intervencao","abordagem.projetos","financiamento.prestacao-de-servico","objeto-de-atuacao.arquitetura-da-edificacao","objeto-de-atuacao.bicicleta","objeto-de-atuacao.infraestrutura","objeto-de-atuacao.meio-ambiente","objeto-de-atuacao.microacessibilidade","objeto-de-atuacao.planejamento-urbano","dificuldades.apoio-politico","dificuldades.financiamento","dificuldades.escassez-de-parcerias"],"estado":"SP","cidade":"São Paulo (SP)"},{"name":"entity.Sao-Paulo-SP.SP.Zoom-Urbanismo-Arquitetura-e-Design","imports":["abordagem.comunicacao","abordagem.educacao","abordagem.intervencao","abordagem.mobilizacao","abordagem.projetos","financiamento.prestacao-de-servico","objeto-de-atuacao.arquitetura-da-edificacao","objeto-de-atuacao.bicicleta","objeto-de-atuacao.infraestrutura","dificuldades.acesso-a-info","dificuldades.apoio-politico","dificuldades.financiamento","dificuldades.burocracia","dificuldades.falta-de-planejamento-estrategico"],"estado":"SP","cidade":"São Paulo (SP)"},{"name":"entity.Sao-Paulo-SP.SP.GEPAF-EACH-USP","imports":["abordagem.comunicacao","abordagem.pesquisa","financiamento.bolsa-de-fomento","financiamento.convenio","financiamento.edital","objeto-de-atuacao.bicicleta","objeto-de-atuacao.infraestrutura","objeto-de-atuacao.saude-e-qualidade-de-vida","dificuldades.financiamento","dificuldades.burocracia","dificuldades.falta-de-colaboradores","dificuldades.falta-de-planejamento-estrategico"],"estado":"SP","cidade":"São Paulo (SP)"},{"name":"entity.Sao-Paulo-SP.SP.Nucleo-de-Pesquisas-Epidemiologicas-em-Nutricao-e-Saude-Faculdade-de-Saude-Publica-Universidade-de-Sao-Paulo","imports":["abordagem.comunicacao","abordagem.educacao","abordagem.legislacao","abordagem.mobilizacao","abordagem.pesquisa","abordagem.projetos","financiamento.bolsa-de-fomento","financiamento.convenio","financiamento.edital","objeto-de-atuacao.bicicleta","objeto-de-atuacao.meio-ambiente","objeto-de-atuacao.planejamento-urbano","objeto-de-atuacao.saude-e-qualidade-de-vida","objeto-de-atuacao.seguranca","objeto-de-atuacao.tecnologia-e-inovacao","dificuldades.financiamento","dificuldades.burocracia","dificuldades.escassez-de-parcerias","dificuldades.escassez-de-voluntarios","dificuldades.apoio-politico"],"estado":"SP","cidade":"São Paulo (SP)"},{"name":"entity.Rio-de-Janeiro-RJ.RJ.Caminha-RIO","imports":["abordagem.comunicacao","abordagem.mobilizacao","financiamento.voluntario","objeto-de-atuacao.infraestrutura","dificuldades.financiamento","dificuldades.escassez-de-voluntarios"],"estado":"RJ","cidade":"Rio de Janeiro (RJ)"},{"name":"entity.Sao-Paulo-SP.SP.Canal-MOVA-SE","imports":["abordagem.comunicacao","financiamento.nenhuma","objeto-de-atuacao.bicicleta","objeto-de-atuacao.infraestrutura","objeto-de-atuacao.microacessibilidade","dificuldades.financiamento"],"estado":"SP","cidade":"São Paulo (SP)"},{"name":"entity.Recife-PE.PE.Calcadas-que-andei","imports":["abordagem.comunicacao","abordagem.intervencao","financiamento.nenhuma","objeto-de-atuacao.infraestrutura","dificuldades.acesso-a-info","dificuldades.apoio-politico","dificuldades.escassez-de-parcerias","dificuldades.escassez-de-voluntarios","dificuldades.falta-de-colaboradores","dificuldades.falta-de-conhecimento","dificuldades.falta-de-planejamento-estrategico","dificuldades.apoio-politico"],"estado":"PE","cidade":"Recife (PE)"},{"name":"entity.Joao-Pessoa-PB.PB.Liberacao-das-calcadas-para-o-transito-de-pedestres","imports":["abordagem.comunicacao","abordagem.mobilizacao","financiamento.nenhuma","objeto-de-atuacao.arquitetura-da-edificacao","objeto-de-atuacao.infraestrutura","objeto-de-atuacao.seguranca"],"estado":"PB","cidade":"João Pessoa (PB)"},{"name":"entity.Sao-Paulo-SP.SP.E-bom-andar-a-pe","imports":["abordagem.comunicacao","financiamento.nenhuma","dificuldades.financiamento"],"estado":"SP","cidade":"São Paulo (SP)"},{"name":"entity.Salvador-BA.BA.Rua-de-Gente","imports":["abordagem.comunicacao","abordagem.educacao","abordagem.pesquisa","abordagem.projetos","financiamento.voluntario","financiamento.nenhuma","objeto-de-atuacao.arquitetura-da-edificacao","objeto-de-atuacao.bicicleta","objeto-de-atuacao.economia","objeto-de-atuacao.infraestrutura","objeto-de-atuacao.microacessibilidade","objeto-de-atuacao.planejamento-urbano","dificuldades.apoio-politico","dificuldades.financiamento","dificuldades.escassez-de-parcerias"],"estado":"BA","cidade":"Salvador (BA)"},{"name":"entity.Sao-Paulo-SP.SP.MUDA-praticas-Ltda","imports":["abordagem.comunicacao","abordagem.educacao","financiamento.edital","financiamento.patrocinio","financiamento.prestacao-de-servico","objeto-de-atuacao.bicicleta","objeto-de-atuacao.infraestrutura","dificuldades.apoio-politico"],"estado":"SP","cidade":"São Paulo (SP)"},{"name":"entity.Sao-Paulo-SP.SP.Mapa-Daqui","imports":["abordagem.intervencao","financiamento.doacao-direta-filantropia","financiamento.edital","financiamento.patrocinio","objeto-de-atuacao.infraestrutura","objeto-de-atuacao.tecnologia-e-inovacao","dificuldades.financiamento","dificuldades.escassez-de-parcerias","dificuldades.escassez-de-voluntarios","dificuldades.falta-de-colaboradores"],"estado":"SP","cidade":"São Paulo (SP)"},{"name":"entity.Belo-Horizonte-MG.MG.Associacao-dos-Ciclistas-Urbanos-de-Belo-Horizonte-BH-em-Ciclo","imports":["abordagem.comunicacao","abordagem.legislacao","financiamento.doacao-direta-membros","financiamento.voluntario","objeto-de-atuacao.bicicleta","objeto-de-atuacao.infraestrutura","dificuldades.capacitacao","dificuldades.escassez-de-voluntarios","dificuldades.falta-de-conhecimento"],"estado":"MG","cidade":"Belo Horizonte (MG)"},{"name":"entity.Teresina-PI.PI.Prefeitura-Municipal-de-orTeresina","imports":[],"estado":"PI","cidade":"Teresina (PI)"},{"name":"entity.Sao-Paulo-SP.SP.SampaPe","imports":["abordagem.comunicacao","abordagem.educacao","abordagem.legislacao","abordagem.mobilizacao","abordagem.pesquisa","financiamento.prestacao-de-servico","objeto-de-atuacao.infraestrutura","objeto-de-atuacao.seguranca","dificuldades.apoio-politico","dificuldades.financiamento"],"estado":"SP","cidade":"São Paulo (SP)"},{"name":"entity.Brasilia-DF.DF.Secretaria-de-Estado-de-Mobilidade-do-Distrito-Federal","imports":["abordagem.comunicacao","abordagem.educacao","abordagem.intervencao","abordagem.legislacao","abordagem.pesquisa","abordagem.projetos","objeto-de-atuacao.arquitetura-da-edificacao","objeto-de-atuacao.bicicleta","objeto-de-atuacao.infraestrutura","objeto-de-atuacao.meio-ambiente","objeto-de-atuacao.microacessibilidade","objeto-de-atuacao.planejamento-urbano","objeto-de-atuacao.seguranca","dificuldades.apoio-politico","dificuldades.falta-de-planejamento-estrategico","dificuldades.apoio-politico"],"estado":"DF","cidade":"Brasília (DF)"},{"name":"entity.Florianopolis-SC.SC.Caminhada-Jane-Jacobs-Floripa","imports":["abordagem.comunicacao","abordagem.educacao","abordagem.mobilizacao","financiamento.voluntario","financiamento.venda-de-produtos","objeto-de-atuacao.arquitetura-da-edificacao","objeto-de-atuacao.infraestrutura","objeto-de-atuacao.planejamento-urbano"],"estado":"SC","cidade":"Florianópolis (SC)"},{"name":"entity.Sao-Paulo-SP.SP.Grupo-de-Trabalho-Mobilidade-Urbana-da-Rede-Butanta","imports":["abordagem.comunicacao","abordagem.educacao","abordagem.mobilizacao","abordagem.pesquisa","abordagem.projetos","financiamento.voluntario","financiamento.nenhuma","objeto-de-atuacao.arquitetura-da-edificacao","objeto-de-atuacao.bicicleta","objeto-de-atuacao.infraestrutura","objeto-de-atuacao.meio-ambiente","objeto-de-atuacao.planejamento-urbano","dificuldades.acesso-a-info","dificuldades.falta-de-colaboradores","dificuldades.falta-de-conhecimento"],"estado":"SP","cidade":"São Paulo (SP)"},{"name":"entity.Sao-Carlos-SP.SP.Genos-Consultoria-Ambiental","imports":["abordagem.comunicacao","abordagem.educacao","abordagem.intervencao","abordagem.legislacao","abordagem.mobilizacao","abordagem.pesquisa","abordagem.projetos","financiamento.prestacao-de-servico","objeto-de-atuacao.arquitetura-da-edificacao","objeto-de-atuacao.bicicleta","objeto-de-atuacao.economia","objeto-de-atuacao.infraestrutura","objeto-de-atuacao.meio-ambiente","objeto-de-atuacao.microacessibilidade","objeto-de-atuacao.planejamento-urbano","objeto-de-atuacao.saude-e-qualidade-de-vida","objeto-de-atuacao.seguranca","objeto-de-atuacao.tecnologia-e-inovacao","dificuldades.apoio-politico","dificuldades.financiamento","dificuldades.burocracia"],"estado":"SP","cidade":"São Carlos (SP)"},{"name":"entity.Sao-Paulo-SP.SP.Urb-i","imports":["abordagem.comunicacao","abordagem.educacao","abordagem.intervencao","abordagem.legislacao","abordagem.mobilizacao","abordagem.pesquisa","abordagem.projetos","financiamento.voluntario","objeto-de-atuacao.arquitetura-da-edificacao","objeto-de-atuacao.bicicleta","objeto-de-atuacao.infraestrutura","objeto-de-atuacao.planejamento-urbano","objeto-de-atuacao.saude-e-qualidade-de-vida","objeto-de-atuacao.seguranca","objeto-de-atuacao.tecnologia-e-inovacao","dificuldades.acesso-a-info","dificuldades.apoio-politico","dificuldades.financiamento","dificuldades.burocracia"],"estado":"SP","cidade":"São Paulo (SP)"},{"name":"entity.Sao-Paulo-SP.SP.PASEOS-A-PIE","imports":["financiamento.voluntario","dificuldades.apoio-politico","dificuldades.financiamento","dificuldades.escassez-de-parcerias"],"estado":"SP","cidade":"São Paulo (SP)"},{"name":"entity.Porto-Alegre-RS.RS.A-Pezito","imports":["abordagem.educacao","abordagem.intervencao","financiamento.nenhuma","objeto-de-atuacao.infraestrutura","objeto-de-atuacao.meio-ambiente","objeto-de-atuacao.saude-e-qualidade-de-vida","objeto-de-atuacao.seguranca","dificuldades.falta-de-colaboradores","dificuldades.falta-de-planejamento-estrategico"],"estado":"RS","cidade":"Porto Alegre (RS)"},{"name":"entity.Fortaleza-CE.CE.Direitos-Urbanos-Fortaleza","imports":["abordagem.comunicacao","abordagem.educacao","abordagem.intervencao","abordagem.mobilizacao","abordagem.projetos","financiamento.doacao-direta-membros","objeto-de-atuacao.arquitetura-da-edificacao","objeto-de-atuacao.bicicleta","objeto-de-atuacao.economia","objeto-de-atuacao.infraestrutura","objeto-de-atuacao.meio-ambiente","objeto-de-atuacao.microacessibilidade","objeto-de-atuacao.planejamento-urbano","objeto-de-atuacao.saude-e-qualidade-de-vida","objeto-de-atuacao.seguranca","objeto-de-atuacao.tecnologia-e-inovacao","dificuldades.acesso-a-info","dificuldades.apoio-politico","dificuldades.burocracia"],"estado":"CE","cidade":"Fortaleza (CE)"},{"name":"entity.Sao-Paulo-SP.SP.Bike-Anjo","imports":["abordagem.comunicacao","abordagem.educacao","abordagem.mobilizacao","financiamento.patrocinio","financiamento.prestacao-de-servico","financiamento.voluntario","objeto-de-atuacao.bicicleta","dificuldades.acesso-a-info","dificuldades.apoio-politico","dificuldades.capacitacao","dificuldades.falta-de-conhecimento","dificuldades.falta-de-planejamento-estrategico"],"estado":"SP","cidade":"São Paulo (SP)"},{"name":"entity.Sao-Paulo-SP.SP.SP-Free-Walking-Tour","imports":["abordagem.comunicacao"],"estado":"SP","cidade":"São Paulo (SP)"},{"name":"entity.Sao-Paulo-SP.SP.Va-de-Bike","imports":["abordagem.comunicacao","abordagem.mobilizacao","financiamento.patrocinio","financiamento.prestacao-de-servico","financiamento.venda-de-produtos","objeto-de-atuacao.bicicleta","objeto-de-atuacao.infraestrutura","objeto-de-atuacao.planejamento-urbano","dificuldades.acesso-a-info","dificuldades.financiamento"],"estado":"SP","cidade":"São Paulo (SP)"},{"name":"entity.Niteroi-RJ.RJ.Bike-Anjo-Niteroi","imports":["abordagem.comunicacao","abordagem.educacao","abordagem.mobilizacao","abordagem.projetos","objeto-de-atuacao.bicicleta","objeto-de-atuacao.meio-ambiente"],"estado":"RJ","cidade":"Niterói (RJ)"},{"name":"entity.Sao-Paulo-SP.SP.IVM-Instituto-Cidade-em-Movimento","imports":["abordagem.comunicacao","abordagem.educacao","abordagem.pesquisa","financiamento.doacao-direta-filantropia","objeto-de-atuacao.infraestrutura","objeto-de-atuacao.microacessibilidade","objeto-de-atuacao.planejamento-urbano","dificuldades.apoio-politico","dificuldades.financiamento","dificuldades.burocracia"],"estado":"SP","cidade":"São Paulo (SP)"},{"name":"entity.Curitiba-PR.PR.Coordenacao-de-Mobilidade-Urbana-CMOB-SETRAN","imports":["abordagem.comunicacao","abordagem.educacao","abordagem.intervencao","abordagem.legislacao","abordagem.projetos","financiamento.orcamento-publico","objeto-de-atuacao.bicicleta","objeto-de-atuacao.infraestrutura","dificuldades.financiamento","dificuldades.burocracia"],"estado":"PR","cidade":"Curitiba (PR)"},{"name":"entity.Brasilia-DF.DF.MOB-Movimente-e-Ocupe-seu-Bairro","imports":["abordagem.comunicacao","abordagem.educacao","abordagem.intervencao","abordagem.mobilizacao","financiamento.voluntario","objeto-de-atuacao.bicicleta","objeto-de-atuacao.infraestrutura","objeto-de-atuacao.microacessibilidade","objeto-de-atuacao.planejamento-urbano","dificuldades.financiamento","dificuldades.burocracia","dificuldades.falta-de-planejamento-estrategico","dificuldades.apoio-politico"],"estado":"DF","cidade":"Brasília (DF)"},{"name":"entity.Sao-Paulo-SP.SP.DESENHE-SUA-FAIXA","imports":["abordagem.comunicacao","abordagem.mobilizacao","financiamento.nenhuma","objeto-de-atuacao.infraestrutura","dificuldades.apoio-politico","dificuldades.burocracia","dificuldades.escassez-de-parcerias"],"estado":"SP","cidade":"São Paulo (SP)"},{"name":"entity.Florianopolis-SC.SC.Rede-Vida-no-Transito-Florianopolis-SC","imports":["abordagem.educacao","abordagem.pesquisa","financiamento.patrocinio","financiamento.voluntario","objeto-de-atuacao.arquitetura-da-edificacao","objeto-de-atuacao.bicicleta","objeto-de-atuacao.infraestrutura","objeto-de-atuacao.microacessibilidade","objeto-de-atuacao.planejamento-urbano","objeto-de-atuacao.seguranca","dificuldades.acesso-a-info"],"estado":"SC","cidade":"Florianópolis (SC)"},{"name":"entity.Florianopolis-SC.SC.MObfloripa","imports":["abordagem.comunicacao","abordagem.educacao","abordagem.mobilizacao","financiamento.convenio","financiamento.doacao-direta-filantropia","financiamento.doacao-direta-membros","financiamento.patrocinio","financiamento.voluntario","objeto-de-atuacao.bicicleta","objeto-de-atuacao.infraestrutura","objeto-de-atuacao.meio-ambiente","objeto-de-atuacao.microacessibilidade","objeto-de-atuacao.saude-e-qualidade-de-vida","objeto-de-atuacao.tecnologia-e-inovacao","dificuldades.apoio-politico","dificuldades.financiamento","dificuldades.capacitacao","dificuldades.falta-de-planejamento-estrategico"],"estado":"SC","cidade":"Florianópolis (SC)"},{"name":"entity.Sao-Paulo-SP.SP.Vigliecca-and-Associados","imports":["abordagem.projetos","financiamento.prestacao-de-servico","objeto-de-atuacao.arquitetura-da-edificacao","objeto-de-atuacao.bicicleta","objeto-de-atuacao.infraestrutura","objeto-de-atuacao.microacessibilidade","objeto-de-atuacao.planejamento-urbano","dificuldades.acesso-a-info","dificuldades.apoio-politico","dificuldades.falta-de-planejamento-estrategico"],"estado":"SP","cidade":"São Paulo (SP)"},{"name":"entity.Sao-Paulo-SP.SP.23-SUL","imports":["abordagem.projetos","financiamento.prestacao-de-servico","objeto-de-atuacao.arquitetura-da-edificacao","objeto-de-atuacao.infraestrutura","objeto-de-atuacao.planejamento-urbano","dificuldades.apoio-politico","dificuldades.financiamento","dificuldades.escassez-de-parcerias","dificuldades.interesse-das-liderancas-da-org"],"estado":"SP","cidade":"São Paulo (SP)"},{"name":"entity.Sao-Paulo-SP.SP.goma-oficina-plataforma-colaborativa","imports":["abordagem.comunicacao","abordagem.educacao","financiamento.prestacao-de-servico","financiamento.venda-de-produtos","objeto-de-atuacao.arquitetura-da-edificacao","objeto-de-atuacao.bicicleta","dificuldades.financiamento"],"estado":"SP","cidade":"São Paulo (SP)"},{"name":"entity.Sao-Paulo-SP.SP.Comissao-Tecnica-de-Mobilidade-a-Pe-e-Acessibilidade-da-Associacao-Nacional-de-Transportes-Publicos","imports":["abordagem.comunicacao","abordagem.educacao","abordagem.legislacao","abordagem.mobilizacao","abordagem.pesquisa","abordagem.projetos","financiamento.convenio","financiamento.edital","financiamento.lei-de-incentivo","financiamento.patrocinio","financiamento.prestacao-de-servico","financiamento.voluntario","financiamento.venda-de-produtos","dificuldades.acesso-a-info","dificuldades.apoio-politico","dificuldades.financiamento","dificuldades.burocracia","dificuldades.capacitacao","dificuldades.escassez-de-parcerias","dificuldades.escassez-de-voluntarios","dificuldades.falta-de-colaboradores","dificuldades.falta-de-planejamento-estrategico","dificuldades.interesse-das-liderancas-da-org","dificuldades.apoio-politico"],"estado":"SP","cidade":"São Paulo (SP)"},{"name":"entity.Sao-Paulo-SP.SP.Pe-de-Igualdade","imports":["abordagem.comunicacao","abordagem.educacao","abordagem.intervencao","abordagem.legislacao","abordagem.mobilizacao","abordagem.pesquisa","abordagem.projetos","financiamento.convenio","financiamento.prestacao-de-servico","financiamento.voluntario","objeto-de-atuacao.arquitetura-da-edificacao","objeto-de-atuacao.bicicleta","objeto-de-atuacao.economia","objeto-de-atuacao.saude-e-qualidade-de-vida","objeto-de-atuacao.seguranca","dificuldades.acesso-a-info","dificuldades.apoio-politico","dificuldades.financiamento","dificuldades.burocracia","dificuldades.escassez-de-parcerias","dificuldades.apoio-politico"],"estado":"SP","cidade":"São Paulo (SP)"},{"name":"entity.Sao-Paulo-SP.SP.Arquipelagos-Urbanos","imports":["abordagem.educacao","abordagem.intervencao","financiamento.doacao-direta-filantropia","financiamento.doacao-direta-membros","financiamento.patrocinio","financiamento.voluntario","objeto-de-atuacao.bicicleta","dificuldades.financiamento","dificuldades.escassez-de-parcerias"],"estado":"SP","cidade":"São Paulo (SP)"},{"name":"entity.Brasilia-DF.DF.Brasilia-para-Pessoas-e-Janes-Walk-Bsb","imports":["abordagem.mobilizacao","abordagem.pesquisa","financiamento.doacao-direta-membros","objeto-de-atuacao.bicicleta","objeto-de-atuacao.infraestrutura","objeto-de-atuacao.planejamento-urbano","dificuldades.financiamento","dificuldades.escassez-de-parcerias","dificuldades.escassez-de-voluntarios","dificuldades.falta-de-colaboradores"],"estado":"DF","cidade":"Brasília (DF)"},{"name":"entity.Sao-Paulo-SP.SP.red-OCARA","imports":["abordagem.comunicacao","abordagem.educacao","abordagem.intervencao","abordagem.mobilizacao","abordagem.pesquisa","financiamento.nenhuma","objeto-de-atuacao.planejamento-urbano","objeto-de-atuacao.saude-e-qualidade-de-vida","objeto-de-atuacao.seguranca","dificuldades.apoio-politico","dificuldades.financiamento","dificuldades.burocracia","dificuldades.escassez-de-parcerias","dificuldades.falta-de-conhecimento"],"estado":"SP","cidade":"São Paulo (SP)"},{"name":"entity.Curitiba-PR.PR.Neourbix","imports":["abordagem.comunicacao","abordagem.educacao","abordagem.legislacao","abordagem.projetos","financiamento.prestacao-de-servico","objeto-de-atuacao.bicicleta","objeto-de-atuacao.infraestrutura","objeto-de-atuacao.microacessibilidade","objeto-de-atuacao.planejamento-urbano","dificuldades.apoio-politico","dificuldades.burocracia","dificuldades.escassez-de-parcerias"],"estado":"PR","cidade":"Curitiba (PR)"},{"name":"entity.Sao-Paulo-SP.SP.Super-Ando","imports":["abordagem.comunicacao","abordagem.educacao","abordagem.mobilizacao","financiamento.nenhuma","dificuldades.financiamento","dificuldades.falta-de-planejamento-estrategico"],"estado":"SP","cidade":"São Paulo (SP)"},{"name":"entity.Governador-Valadares-MG.MG.Prefeitura-Municipal-de-Governador-Valadares","imports":["abordagem.legislacao","financiamento.orcamento-publico","objeto-de-atuacao.arquitetura-da-edificacao","objeto-de-atuacao.economia","objeto-de-atuacao.infraestrutura","objeto-de-atuacao.planejamento-urbano","dificuldades.acesso-a-info","dificuldades.apoio-politico","dificuldades.financiamento","dificuldades.capacitacao"],"estado":"MG","cidade":"Governador Valadares (MG)"},{"name":"entity.Campinas-SP.SP.EMDEC","imports":["abordagem.educacao","abordagem.intervencao","abordagem.legislacao","abordagem.pesquisa","abordagem.projetos","financiamento.convenio","financiamento.prestacao-de-servico","objeto-de-atuacao.bicicleta","objeto-de-atuacao.microacessibilidade","objeto-de-atuacao.planejamento-urbano","dificuldades.financiamento","dificuldades.burocracia","dificuldades.falta-de-planejamento-estrategico","dificuldades.interesse-das-liderancas-da-org"],"estado":"SP","cidade":"Campinas (SP)"},{"name":"entity.Cuiaba-MT.MT.Secretaria-Municipal-de-Ordem-Publica","imports":["abordagem.legislacao","financiamento.orcamento-publico","objeto-de-atuacao.planejamento-urbano","dificuldades.financiamento"],"estado":"MT","cidade":"Cuiabá (MT)"},{"name":"entity.Sao-Paulo-SP.SP.Bela-Rua","imports":["abordagem.educacao","abordagem.intervencao","financiamento.prestacao-de-servico","objeto-de-atuacao.arquitetura-da-edificacao","dificuldades.financiamento","dificuldades.burocracia"],"estado":"SP","cidade":"São Paulo (SP)"},{"name":"entity.Goiania-GO.GO.Forum-de-Mobilidade-Urbana-da-Regiao-Metropolitana-de-Goiania","imports":["abordagem.comunicacao","financiamento.edital","objeto-de-atuacao.microacessibilidade","objeto-de-atuacao.planejamento-urbano","dificuldades.apoio-politico","dificuldades.financiamento","dificuldades.apoio-politico"],"estado":"GO","cidade":"Goiânia (GO)"},{"name":"entity.Sao-Paulo-SP.SP.Vila-a-30","imports":["abordagem.comunicacao","financiamento.voluntario","objeto-de-atuacao.arquitetura-da-edificacao","objeto-de-atuacao.bicicleta","objeto-de-atuacao.economia","objeto-de-atuacao.infraestrutura","objeto-de-atuacao.meio-ambiente","objeto-de-atuacao.microacessibilidade","dificuldades.escassez-de-voluntarios","dificuldades.falta-de-colaboradores"],"estado":"SP","cidade":"São Paulo (SP)"},{"name":"entity.Sao-Paulo-SP.SP.Giro-Inclusivo-e-Biomob","imports":["abordagem.educacao","financiamento.doacao-direta-filantropia","financiamento.crowdfunding","financiamento.patrocinio","objeto-de-atuacao.arquitetura-da-edificacao","objeto-de-atuacao.infraestrutura","objeto-de-atuacao.microacessibilidade","objeto-de-atuacao.planejamento-urbano","objeto-de-atuacao.saude-e-qualidade-de-vida","dificuldades.financiamento","dificuldades.escassez-de-parcerias"],"estado":"SP","cidade":"São Paulo (SP)"},{"name":"entity.Joinville-SC.SC.Diverte-Inverte","imports":["abordagem.intervencao","financiamento.nenhuma","objeto-de-atuacao.bicicleta","dificuldades.financiamento","dificuldades.escassez-de-voluntarios"],"estado":"SC","cidade":"Joinville (SC)"},{"name":"entity.Sao-Paulo-SP.SP.silviaeninaorg","imports":["abordagem.mobilizacao","financiamento.nenhuma","objeto-de-atuacao.bicicleta","objeto-de-atuacao.infraestrutura","objeto-de-atuacao.meio-ambiente","objeto-de-atuacao.saude-e-qualidade-de-vida"],"estado":"SP","cidade":"São Paulo (SP)"},{"name":"entity.Sao-Paulo-SP.SP.Caminhadas-Urbanas","imports":["abordagem.comunicacao","financiamento.voluntario"],"estado":"SP","cidade":"São Paulo (SP)"},{"name":"entity.Vitoria-ES.ES.Pedestre-se","imports":["abordagem.comunicacao","financiamento.voluntario","objeto-de-atuacao.infraestrutura","dificuldades.falta-de-colaboradores"],"estado":"ES","cidade":"Vitória (ES)"},{"name":"entity.Goiania-GO.GO.Sobreurbana","imports":["abordagem.comunicacao","abordagem.intervencao","abordagem.mobilizacao","financiamento.edital","financiamento.crowdfunding","financiamento.patrocinio","financiamento.prestacao-de-servico","financiamento.nenhuma","objeto-de-atuacao.bicicleta","objeto-de-atuacao.infraestrutura","objeto-de-atuacao.meio-ambiente","dificuldades.financiamento"],"estado":"GO","cidade":"Goiânia (GO)"},{"name":"entity.Sao-Paulo-SP.SP.Caminhada-das-QUEBRADAS","imports":["abordagem.educacao","abordagem.intervencao","abordagem.mobilizacao","financiamento.patrocinio","financiamento.venda-de-produtos","objeto-de-atuacao.infraestrutura","objeto-de-atuacao.saude-e-qualidade-de-vida","dificuldades.apoio-politico","dificuldades.financiamento","dificuldades.escassez-de-parcerias","dificuldades.falta-de-colaboradores"],"estado":"SP","cidade":"São Paulo (SP)"},{"name":"entity.Sao-Paulo-SP.SP.Solucoes-para-Cidades-ABCP","imports":["abordagem.comunicacao","abordagem.educacao","abordagem.intervencao","abordagem.legislacao","abordagem.mobilizacao","financiamento.doacao-direta-membros","objeto-de-atuacao.arquitetura-da-edificacao","objeto-de-atuacao.bicicleta","objeto-de-atuacao.economia","objeto-de-atuacao.infraestrutura","objeto-de-atuacao.meio-ambiente","objeto-de-atuacao.planejamento-urbano","objeto-de-atuacao.seguranca","dificuldades.financiamento","dificuldades.falta-de-planejamento-estrategico","dificuldades.apoio-politico"],"estado":"SP","cidade":"São Paulo (SP)"},{"name":"entity.Sao-Paulo-SP.SP.Milala-A-Liberdade-de-Ir-e-Vir","imports":["abordagem.comunicacao","abordagem.educacao","abordagem.mobilizacao","financiamento.nenhuma","objeto-de-atuacao.infraestrutura","dificuldades.apoio-politico","dificuldades.financiamento"],"estado":"SP","cidade":"São Paulo (SP)"},{"name":"entity.Sao-Paulo-SP.SP.PingPoint","imports":["abordagem.intervencao","financiamento.crowdfunding","financiamento.venda-de-produtos","financiamento.nenhuma","objeto-de-atuacao.infraestrutura"],"estado":"SP","cidade":"São Paulo (SP)"},{"name":"entity.Sao-Paulo-SP.SP.Parqueleta","imports":["abordagem.intervencao","financiamento.venda-de-produtos","objeto-de-atuacao.bicicleta","objeto-de-atuacao.infraestrutura","dificuldades.falta-de-conhecimento"],"estado":"SP","cidade":"São Paulo (SP)"},{"name":"entity.Sao-Paulo-SP.SP.Desbravadores-de-Sampa","imports":["abordagem.comunicacao","abordagem.pesquisa","financiamento.doacao-direta-membros","objeto-de-atuacao.arquitetura-da-edificacao","objeto-de-atuacao.meio-ambiente","objeto-de-atuacao.saude-e-qualidade-de-vida","dificuldades.financiamento","dificuldades.capacitacao","dificuldades.falta-de-planejamento-estrategico"],"estado":"SP","cidade":"São Paulo (SP)"},{"name":"entity.Belo-Horizonte-MG.MG.BHTRANS-Empresa-de-Transportes-e-Transito-de-belo-Horizonte","imports":["abordagem.projetos","financiamento.orcamento-publico","objeto-de-atuacao.infraestrutura","objeto-de-atuacao.meio-ambiente","objeto-de-atuacao.microacessibilidade","objeto-de-atuacao.planejamento-urbano","dificuldades.apoio-politico","dificuldades.financiamento","dificuldades.burocracia","dificuldades.interesse-das-liderancas-da-org"],"estado":"MG","cidade":"Belo Horizonte (MG)"},{"name":"entity.Sao-Paulo-SP.SP.Carona-a-Pe","imports":["abordagem.educacao","financiamento.nenhuma","objeto-de-atuacao.infraestrutura","objeto-de-atuacao.saude-e-qualidade-de-vida","dificuldades.apoio-politico","dificuldades.escassez-de-parcerias","dificuldades.interesse-das-liderancas-da-org"],"estado":"SP","cidade":"São Paulo (SP)"},{"name":"entity.Manaus-AM.AM.Pedala-Manaus","imports":["abordagem.comunicacao","abordagem.mobilizacao","financiamento.nenhuma","objeto-de-atuacao.bicicleta","objeto-de-atuacao.infraestrutura","dificuldades.apoio-politico","dificuldades.financiamento","dificuldades.capacitacao","dificuldades.escassez-de-voluntarios"],"estado":"AM","cidade":"Manaus (AM)"},{"name":"entity.Rio-de-Janeiro-RJ.RJ.Instituto-de-Politicas-de-Transporte-e-Desenvolvimento","imports":["abordagem.comunicacao","abordagem.intervencao","abordagem.legislacao","abordagem.pesquisa","abordagem.projetos","financiamento.doacao-direta-filantropia","financiamento.edital","objeto-de-atuacao.arquitetura-da-edificacao","objeto-de-atuacao.bicicleta","objeto-de-atuacao.infraestrutura","objeto-de-atuacao.meio-ambiente","objeto-de-atuacao.microacessibilidade","objeto-de-atuacao.planejamento-urbano","objeto-de-atuacao.seguranca","dificuldades.apoio-politico","dificuldades.falta-de-conhecimento","dificuldades.apoio-politico"],"estado":"RJ","cidade":"Rio de Janeiro (RJ)"},{"name":"entity.Sao-Paulo-SP.SP.Calcada-Livre","imports":["abordagem.comunicacao","abordagem.educacao","abordagem.intervencao","abordagem.mobilizacao","abordagem.pesquisa","financiamento.nenhuma","objeto-de-atuacao.infraestrutura","dificuldades.apoio-politico","dificuldades.financiamento","dificuldades.burocracia","dificuldades.falta-de-conhecimento","dificuldades.falta-de-planejamento-estrategico"],"estado":"SP","cidade":"São Paulo (SP)"},{"name":"entity.Campinas-SP.SP.The-MIX-Bazar","imports":["abordagem.intervencao","financiamento.venda-de-produtos","financiamento.nenhuma","objeto-de-atuacao.economia"],"estado":"SP","cidade":"Campinas (SP)"},{"name":"entity.Sao-Paulo-SP.SP.CalcadaSP","imports":["abordagem.comunicacao","abordagem.educacao","abordagem.intervencao","abordagem.mobilizacao","financiamento.nenhuma","dificuldades.financiamento","dificuldades.escassez-de-parcerias","dificuldades.escassez-de-voluntarios"],"estado":"SP","cidade":"São Paulo (SP)"},{"name":"entity.Sao-Paulo-SP.SP.Coletivo-Rodas-de-Leitura","imports":["abordagem.intervencao","financiamento.doacao-direta-filantropia","financiamento.prestacao-de-servico","financiamento.voluntario","objeto-de-atuacao.bicicleta","dificuldades.falta-de-colaboradores"],"estado":"SP","cidade":"São Paulo (SP)"},{"name":"entity.Recife-PE.PE.Janes-Walk","imports":["abordagem.comunicacao","abordagem.educacao","abordagem.mobilizacao","financiamento.nenhuma","objeto-de-atuacao.arquitetura-da-edificacao","objeto-de-atuacao.infraestrutura","objeto-de-atuacao.planejamento-urbano","dificuldades.financiamento"],"estado":"PE","cidade":"Recife (PE)"},{"name":"entity.Belo-Horizonte-MG.MG.TECTRAN-Grupo-SYSTRA","imports":["abordagem.legislacao","abordagem.pesquisa","abordagem.projetos","financiamento.edital","financiamento.prestacao-de-servico","financiamento.venda-de-produtos","objeto-de-atuacao.bicicleta","objeto-de-atuacao.economia","objeto-de-atuacao.infraestrutura","objeto-de-atuacao.meio-ambiente","objeto-de-atuacao.microacessibilidade","objeto-de-atuacao.planejamento-urbano","objeto-de-atuacao.seguranca","objeto-de-atuacao.tecnologia-e-inovacao","dificuldades.acesso-a-info","dificuldades.apoio-politico"],"estado":"MG","cidade":"Belo Horizonte (MG)"},{"name":"entity.Garopaba-SC.SC.Minha-Garopaba-Rede-Nossas-Cidades","imports":["objeto-de-atuacao.arquitetura-da-edificacao","objeto-de-atuacao.bicicleta","objeto-de-atuacao.economia","objeto-de-atuacao.infraestrutura","objeto-de-atuacao.meio-ambiente","objeto-de-atuacao.microacessibilidade","objeto-de-atuacao.planejamento-urbano","objeto-de-atuacao.seguranca","objeto-de-atuacao.tecnologia-e-inovacao","dificuldades.escassez-de-voluntarios","dificuldades.falta-de-colaboradores","dificuldades.falta-de-planejamento-estrategico"],"estado":"SC","cidade":"Garopaba (SC)"},{"name":"entity.Goiania-GO.GO.SECRETARIA-MUNICIPAL-DE-TRANSITO-TRANSPORTES-E-MOBILIDADE-SMT","imports":["abordagem.comunicacao","abordagem.educacao","abordagem.intervencao","abordagem.projetos","financiamento.orcamento-publico","objeto-de-atuacao.bicicleta","objeto-de-atuacao.infraestrutura","objeto-de-atuacao.planejamento-urbano","dificuldades.apoio-politico","dificuldades.financiamento","dificuldades.capacitacao","dificuldades.escassez-de-parcerias","dificuldades.escassez-de-voluntarios","dificuldades.apoio-politico"],"estado":"GO","cidade":"Goiânia (GO)"},{"name":"entity.Sao-Paulo-SP.SP.Camara-Tematica-de-Mobilidade-a-Pe-do-CMTT","imports":["abordagem.comunicacao","abordagem.legislacao","abordagem.mobilizacao","financiamento.nenhuma","objeto-de-atuacao.infraestrutura","objeto-de-atuacao.microacessibilidade","objeto-de-atuacao.planejamento-urbano","dificuldades.acesso-a-info","dificuldades.apoio-politico","dificuldades.escassez-de-voluntarios","dificuldades.falta-de-planejamento-estrategico","dificuldades.apoio-politico"],"estado":"SP","cidade":"São Paulo (SP)"},{"name":"entity.Curitiba-PR.PR.Vaga-Viva-Instituto-Energia-Humana","imports":["abordagem.comunicacao","abordagem.educacao","abordagem.mobilizacao","abordagem.pesquisa","abordagem.projetos","financiamento.prestacao-de-servico","objeto-de-atuacao.bicicleta","objeto-de-atuacao.infraestrutura","objeto-de-atuacao.meio-ambiente","dificuldades.apoio-politico","dificuldades.escassez-de-voluntarios"],"estado":"PR","cidade":"Curitiba (PR)"},{"name":"entity.Recife-PE.PE.Ameciclo-Associacao-Metropolitana-de-Ciclistas-do-Grande-Recife","imports":["abordagem.comunicacao","abordagem.educacao","abordagem.intervencao","abordagem.projetos","financiamento.doacao-direta-membros","financiamento.edital","financiamento.crowdfunding","financiamento.prestacao-de-servico","objeto-de-atuacao.bicicleta","objeto-de-atuacao.economia","objeto-de-atuacao.infraestrutura","objeto-de-atuacao.meio-ambiente","objeto-de-atuacao.microacessibilidade","objeto-de-atuacao.planejamento-urbano","objeto-de-atuacao.seguranca","objeto-de-atuacao.tecnologia-e-inovacao","dificuldades.apoio-politico","dificuldades.capacitacao","dificuldades.escassez-de-voluntarios","dificuldades.interesse-das-liderancas-da-org","dificuldades.apoio-politico"],"estado":"PE","cidade":"Recife (PE)"},{"name":"entity..SP.untourism","imports":["abordagem.comunicacao","abordagem.educacao","abordagem.mobilizacao","financiamento.prestacao-de-servico","objeto-de-atuacao.arquitetura-da-edificacao","objeto-de-atuacao.economia","objeto-de-atuacao.meio-ambiente","objeto-de-atuacao.planejamento-urbano","objeto-de-atuacao.tecnologia-e-inovacao","dificuldades.escassez-de-parcerias","dificuldades.falta-de-planejamento-estrategico"],"estado":"SP","cidade":""},{"name":"entity.Curitiba-PR.PR.Associacao-de-Ciclistas-do-Alto-Iguacu","imports":["abordagem.comunicacao","abordagem.educacao","abordagem.legislacao","abordagem.mobilizacao","abordagem.pesquisa","abordagem.projetos","financiamento.edital","objeto-de-atuacao.bicicleta","objeto-de-atuacao.economia","objeto-de-atuacao.infraestrutura","objeto-de-atuacao.meio-ambiente","objeto-de-atuacao.microacessibilidade","objeto-de-atuacao.planejamento-urbano","objeto-de-atuacao.seguranca","objeto-de-atuacao.tecnologia-e-inovacao","dificuldades.escassez-de-voluntarios","dificuldades.falta-de-colaboradores","dificuldades.falta-de-planejamento-estrategico","dificuldades.apoio-politico"],"estado":"PR","cidade":"Curitiba (PR)"},{"name":"entity.Brasilia-DF.DF.Instituto-do-Movimento-Nacional-pelo-Direito-ao-transporte-Publico-de-Qualidade-para-Todos","imports":["abordagem.comunicacao","abordagem.educacao","abordagem.legislacao","abordagem.mobilizacao","financiamento.doacao-direta-membros","objeto-de-atuacao.infraestrutura","objeto-de-atuacao.meio-ambiente","objeto-de-atuacao.planejamento-urbano","dificuldades.apoio-politico","dificuldades.financiamento","dificuldades.capacitacao","dificuldades.apoio-politico"],"estado":"DF","cidade":"Brasília (DF)"},{"name":"entity.Salvador-BA.BA.Secretaria-de-Municipal-de-Mobilidade-de-Salvador","imports":["financiamento.orcamento-publico","objeto-de-atuacao.bicicleta","objeto-de-atuacao.infraestrutura","objeto-de-atuacao.planejamento-urbano"],"estado":"BA","cidade":"Salvador (BA)"},{"name":"entity.Sao-Paulo-SP.SP.Instituto-A-Cidade-Precisa-de-Voce","imports":["abordagem.comunicacao","abordagem.educacao","abordagem.intervencao","abordagem.legislacao","abordagem.mobilizacao","abordagem.pesquisa","abordagem.projetos","financiamento.doacao-direta-filantropia","financiamento.doacao-direta-membros","financiamento.edital","financiamento.crowdfunding","financiamento.prestacao-de-servico","financiamento.voluntario","objeto-de-atuacao.infraestrutura","objeto-de-atuacao.planejamento-urbano","dificuldades.financiamento"],"estado":"SP","cidade":"São Paulo (SP)"},{"name":"entity.Sao-Paulo-SP.SP.ape-estudos-em-mobilidade","imports":["abordagem.educacao","abordagem.intervencao","abordagem.legislacao","abordagem.mobilizacao","abordagem.pesquisa","abordagem.projetos","financiamento.doacao-direta-filantropia","financiamento.prestacao-de-servico","objeto-de-atuacao.infraestrutura","objeto-de-atuacao.meio-ambiente","objeto-de-atuacao.microacessibilidade","objeto-de-atuacao.planejamento-urbano","objeto-de-atuacao.seguranca","dificuldades.financiamento"],"estado":"SP","cidade":"São Paulo (SP)"},{"name":"entity.Sao-Paulo-SP.SP.Fatec-Ipiranga","imports":["abordagem.mobilizacao","objeto-de-atuacao.meio-ambiente","dificuldades.financiamento","dificuldades.capacitacao","dificuldades.falta-de-colaboradores"],"estado":"SP","cidade":"São Paulo (SP)"},{"name":"entity.Sao-Paulo-SP.SP.Coletivo-Nao-So-o-Gato","imports":["abordagem.mobilizacao","financiamento.nenhuma","dificuldades.escassez-de-voluntarios"],"estado":"SP","cidade":"São Paulo (SP)"},{"name":"entity.Sao-Paulo-SP.SP.Instituto-Mobilidade-Verde","imports":["abordagem.intervencao","abordagem.legislacao","abordagem.pesquisa","abordagem.projetos","financiamento.doacao-direta-filantropia","financiamento.patrocinio","objeto-de-atuacao.arquitetura-da-edificacao","objeto-de-atuacao.bicicleta","objeto-de-atuacao.economia","objeto-de-atuacao.infraestrutura","objeto-de-atuacao.meio-ambiente","objeto-de-atuacao.microacessibilidade","objeto-de-atuacao.planejamento-urbano","objeto-de-atuacao.seguranca","objeto-de-atuacao.tecnologia-e-inovacao","dificuldades.escassez-de-voluntarios"],"estado":"SP","cidade":"São Paulo (SP)"},{"name":"entity.Sao-Paulo-SP.SP.Basurama-Brasil","imports":["abordagem.projetos","financiamento.orcamento-publico","financiamento.prestacao-de-servico","financiamento.voluntario","objeto-de-atuacao.arquitetura-da-edificacao","objeto-de-atuacao.bicicleta","objeto-de-atuacao.infraestrutura","objeto-de-atuacao.planejamento-urbano","objeto-de-atuacao.tecnologia-e-inovacao","dificuldades.apoio-politico","dificuldades.financiamento","dificuldades.falta-de-conhecimento"],"estado":"SP","cidade":"São Paulo (SP)"},{"name":"entity.Maceio-AL.AL.Ciclomobilidade-Associacao-de-Ciclistas-Urbanos-de-Maceio","imports":["abordagem.mobilizacao","abordagem.pesquisa","financiamento.edital","financiamento.nenhuma","objeto-de-atuacao.bicicleta","dificuldades.acesso-a-info","dificuldades.apoio-politico"],"estado":"AL","cidade":"Maceió (AL)"},{"name":"entity.Campo-Grande-MS.MS.CIDADE-AMBIENTE-PROJETOS-RESPONSAVEIS-LTDA","imports":["abordagem.projetos","financiamento.orcamento-publico","financiamento.prestacao-de-servico","objeto-de-atuacao.arquitetura-da-edificacao","objeto-de-atuacao.bicicleta","objeto-de-atuacao.infraestrutura","objeto-de-atuacao.meio-ambiente","objeto-de-atuacao.planejamento-urbano","dificuldades.apoio-politico","dificuldades.escassez-de-parcerias","dificuldades.falta-de-conhecimento"],"estado":"MS","cidade":"Campo Grande (MS)"},{"name":"entity.Sao-Paulo-SP.SP.Projeto-A-Pe","imports":["abordagem.comunicacao","financiamento.nenhuma","dificuldades.financiamento"],"estado":"SP","cidade":"São Paulo (SP)"},{"name":"entity.Sao-Paulo-SP.SP.places-for-us","imports":["abordagem.comunicacao","abordagem.projetos","objeto-de-atuacao.arquitetura-da-edificacao","objeto-de-atuacao.bicicleta","objeto-de-atuacao.economia","objeto-de-atuacao.planejamento-urbano","objeto-de-atuacao.saude-e-qualidade-de-vida","objeto-de-atuacao.tecnologia-e-inovacao"],"estado":"SP","cidade":"São Paulo (SP)"},{"name":"entity.Sao-Jose-dos-Campos-SP.SP.Prefeitura-Municipal-Sao-Jose-dos-Campos-ST-Scretaria-de-Transportes-Programa-Calcada-Segura","imports":["abordagem.intervencao","abordagem.legislacao","abordagem.projetos","financiamento.orcamento-publico","objeto-de-atuacao.arquitetura-da-edificacao","objeto-de-atuacao.bicicleta","objeto-de-atuacao.infraestrutura","objeto-de-atuacao.planejamento-urbano","dificuldades.acesso-a-info","dificuldades.capacitacao","dificuldades.escassez-de-parcerias","dificuldades.falta-de-colaboradores","dificuldades.apoio-politico"],"estado":"SP","cidade":"São José dos Campos (SP)"},{"name":"entity.Sao-Paulo-SP.SP.Via-trolebus","imports":["abordagem.comunicacao","abordagem.educacao","abordagem.intervencao","financiamento.nenhuma","objeto-de-atuacao.bicicleta","objeto-de-atuacao.infraestrutura","objeto-de-atuacao.microacessibilidade","dificuldades.acesso-a-info"],"estado":"SP","cidade":"São Paulo (SP)"},{"name":"entity.Sao-Paulo-SP.SP.cidades-sem-fronteiras","imports":["abordagem.comunicacao","financiamento.prestacao-de-servico","objeto-de-atuacao.arquitetura-da-edificacao","objeto-de-atuacao.economia","objeto-de-atuacao.planejamento-urbano","dificuldades.financiamento","dificuldades.falta-de-colaboradores"],"estado":"SP","cidade":"São Paulo (SP)"},{"name":"entity.Sao-Paulo-SP.SP.Outra-Cidade","imports":["abordagem.comunicacao","financiamento.patrocinio","objeto-de-atuacao.arquitetura-da-edificacao","objeto-de-atuacao.bicicleta","objeto-de-atuacao.economia","objeto-de-atuacao.infraestrutura","objeto-de-atuacao.meio-ambiente","objeto-de-atuacao.microacessibilidade","objeto-de-atuacao.planejamento-urbano","objeto-de-atuacao.saude-e-qualidade-de-vida","objeto-de-atuacao.seguranca","objeto-de-atuacao.tecnologia-e-inovacao","dificuldades.acesso-a-info","dificuldades.escassez-de-parcerias"],"estado":"SP","cidade":"São Paulo (SP)"},{"name":"entity.Sao-Paulo-SP.SP.Colabre","imports":["abordagem.pesquisa","financiamento.patrocinio","financiamento.venda-de-produtos","objeto-de-atuacao.tecnologia-e-inovacao","dificuldades.interesse-das-liderancas-da-org"],"estado":"SP","cidade":"São Paulo (SP)"},{"name":"entity.Porto-Velho-RO.RO.COMISSAO-ESPECIFICA-PERMANENTE-DE-CALCADAS-CEPC","imports":["abordagem.intervencao","abordagem.legislacao","abordagem.projetos","financiamento.orcamento-publico","objeto-de-atuacao.infraestrutura","dificuldades.burocracia","dificuldades.apoio-politico"],"estado":"RO","cidade":"Porto Velho (RO)"},{"name":"entity.Rio-de-Janeiro-RJ.RJ.Centro-de-Criacao-de-Imagem-Popular","imports":["abordagem.mobilizacao","abordagem.pesquisa","abordagem.projetos","financiamento.edital","objeto-de-atuacao.infraestrutura","objeto-de-atuacao.planejamento-urbano","dificuldades.apoio-politico","dificuldades.financiamento","dificuldades.capacitacao","dificuldades.escassez-de-parcerias"],"estado":"RJ","cidade":"Rio de Janeiro (RJ)"},{"name":"entity..SP.Blog-Passeios-Baratos-em-SP","imports":["abordagem.comunicacao","financiamento.prestacao-de-servico","dificuldades.financiamento","dificuldades.escassez-de-parcerias","dificuldades.falta-de-colaboradores"],"estado":"SP","cidade":""},{"name":"entity.Belo-Horizonte-MG.MG.Micropolis","imports":["abordagem.comunicacao","abordagem.educacao","abordagem.pesquisa","abordagem.projetos","financiamento.edital","financiamento.lei-de-incentivo","financiamento.prestacao-de-servico","objeto-de-atuacao.arquitetura-da-edificacao","objeto-de-atuacao.infraestrutura","objeto-de-atuacao.planejamento-urbano","dificuldades.acesso-a-info"],"estado":"MG","cidade":"Belo Horizonte (MG)"},{"name":"entity.Sao-Paulo-SP.SP.Scipopulis","imports":["abordagem.comunicacao","abordagem.mobilizacao","financiamento.bolsa-de-fomento","financiamento.edital","financiamento.prestacao-de-servico","objeto-de-atuacao.microacessibilidade","objeto-de-atuacao.planejamento-urbano","dificuldades.burocracia"],"estado":"SP","cidade":"São Paulo (SP)"},{"name":"entity.Porto-Alegre-RS.RS.Freewalk-POA","imports":["abordagem.intervencao","abordagem.mobilizacao","objeto-de-atuacao.arquitetura-da-edificacao","objeto-de-atuacao.bicicleta","objeto-de-atuacao.tecnologia-e-inovacao","dificuldades.apoio-politico","dificuldades.financiamento","dificuldades.burocracia"],"estado":"RS","cidade":"Porto Alegre (RS)"},{"name":"entity.Sao-Paulo-SP.SP.Greenpeace","imports":["abordagem.intervencao","abordagem.legislacao","abordagem.mobilizacao","financiamento.doacao-direta-membros","financiamento.crowdfunding","objeto-de-atuacao.meio-ambiente","dificuldades.apoio-politico"],"estado":"SP","cidade":"São Paulo (SP)"},{"name":"abordagem.comunicacao","count":65,"totalEntityCount":108},{"name":"abordagem.educacao","count":50,"totalEntityCount":108},{"name":"abordagem.intervencao","count":39,"totalEntityCount":108},{"name":"abordagem.legislacao","count":28,"totalEntityCount":108},{"name":"abordagem.mobilizacao","count":48,"totalEntityCount":108},{"name":"abordagem.pesquisa","count":32,"totalEntityCount":108},{"name":"abordagem.projetos","count":35,"totalEntityCount":108},{"name":"financiamento.bolsa-de-fomento","count":3,"totalEntityCount":108},{"name":"financiamento.convenio","count":6,"totalEntityCount":108},{"name":"financiamento.doacao-direta-filantropia","count":14,"totalEntityCount":108},{"name":"financiamento.doacao-direta-membros","count":11,"totalEntityCount":108},{"name":"financiamento.edital","count":17,"totalEntityCount":108},{"name":"financiamento.crowdfunding","count":6,"totalEntityCount":108},{"name":"financiamento.lei-de-incentivo","count":2,"totalEntityCount":108},{"name":"financiamento.orcamento-publico","count":10,"totalEntityCount":108},{"name":"financiamento.patrocinio","count":15,"totalEntityCount":108},{"name":"financiamento.prestacao-de-servico","count":31,"totalEntityCount":108},{"name":"financiamento.voluntario","count":22,"totalEntityCount":108},{"name":"financiamento.venda-de-produtos","count":11,"totalEntityCount":108},{"name":"financiamento.nenhuma","count":27,"totalEntityCount":108},{"name":"objeto-de-atuacao.arquitetura-da-edificacao","count":34,"totalEntityCount":108},{"name":"objeto-de-atuacao.bicicleta","count":54,"totalEntityCount":108},{"name":"objeto-de-atuacao.economia","count":17,"totalEntityCount":108},{"name":"objeto-de-atuacao.infraestrutura","count":72,"totalEntityCount":108},{"name":"objeto-de-atuacao.meio-ambiente","count":30,"totalEntityCount":108},{"name":"objeto-de-atuacao.microacessibilidade","count":31,"totalEntityCount":108},{"name":"objeto-de-atuacao.planejamento-urbano","count":52,"totalEntityCount":108},{"name":"objeto-de-atuacao.saude-e-qualidade-de-vida","count":19,"totalEntityCount":108},{"name":"objeto-de-atuacao.seguranca","count":20,"totalEntityCount":108},{"name":"objeto-de-atuacao.tecnologia-e-inovacao","count":19,"totalEntityCount":108},{"name":"dificuldades.acesso-a-info","count":20,"totalEntityCount":108},{"name":"dificuldades.apoio-politico","count":50,"totalEntityCount":108},{"name":"dificuldades.financiamento","count":57,"totalEntityCount":108},{"name":"dificuldades.burocracia","count":21,"totalEntityCount":108},{"name":"dificuldades.capacitacao","count":13,"totalEntityCount":108},{"name":"dificuldades.escassez-de-parcerias","count":25,"totalEntityCount":108},{"name":"dificuldades.escassez-de-voluntarios","count":21,"totalEntityCount":108},{"name":"dificuldades.falta-de-colaboradores","count":17,"totalEntityCount":108},{"name":"dificuldades.falta-de-conhecimento","count":11,"totalEntityCount":108},{"name":"dificuldades.falta-de-planejamento-estrategico","count":19,"totalEntityCount":108},{"name":"dificuldades.interesse-das-liderancas-da-org","count":7,"totalEntityCount":108}]